passwordgenerator_uz/__init__.py
passwordgenerator_uz-0.0.1.dist-info/METADATA
passwordgenerator_uz-0.0.1.dist-info/WHEEL
passwordgenerator_uz-0.0.1.dist-info/top_level.txt
passwordgenerator_uz-0.0.1.dist-info/RECORD
