Metadata-Version: 2.1
Name: passwordgenerator-uz
Version: 0.0.1
Summary: Ushbu kutubxona yordamida parol generatsiya qilib olishingiz mumkin!
Author: Ozodbek Sobirjonovich
Author-email: ozodbeksobirjonovich@gmail.com
